pytest_result_sender_r-0.1.20.dist-info/METADATA
pytest_result_sender_r-0.1.20.dist-info/WHEEL
pytest_result_sender_r-0.1.20.dist-info/entry_points.txt
pytest_result_sender_r/__init__.py
pytest_result_sender_r/plugin.py
pytest_result_sender_r-0.1.20.dist-info/RECORD
