Metadata-Version: 2.1
Name: pytest-result-sender-r
Version: 0.1.20
Summary: Default template for PDM package
Author-Email: yoaonoge <yoaonoge@163.com>
License: MIT
Requires-Python: >=3.9
Requires-Dist: pytest>=8.4.2
Requires-Dist: black>=25.11.0
Requires-Dist: isort>=6.1.0
Requires-Dist: flake8>=7.3.0
Requires-Dist: requests>=2.32.5
